{
  "dictionary_name": "DICT_6X6_50",
  "marker_length_mm": 100.0,
  "goal_width_m": 2.09,
  "goal_height_m": 1.56,
  "scoring_plane_depth_m": 0.1,
  "opening_inset_left_m": 0.1,
  "opening_inset_right_m": 0.1,
  "opening_inset_top_m": 0.1,
  "opening_inset_bottom_m": 0.1,
  "markers": [
    {
      "marker_id": 10,
      "name": "top-left",
      "center_m": [
        0.05,
        0.05,
        0.0
      ]
    },
    {
      "marker_id": 11,
      "name": "top-right",
      "center_m": [
        2.04,
        0.05,
        0.0
      ]
    },
    {
      "marker_id": 12,
      "name": "mid-left",
      "center_m": [
        0.05,
        0.66,
        0.0
      ]
    },
    {
      "marker_id": 13,
      "name": "mid-right",
      "center_m": [
        2.04,
        0.66,
        0.0
      ]
    },
    {
      "marker_id": 14,
      "name": "bottom-left",
      "center_m": [
        0.05,
        1.51,
        0.0
      ]
    },
    {
      "marker_id": 15,
      "name": "bottom-right",
      "center_m": [
        2.04,
        1.51,
        0.0
      ]
    }
  ]
}
